{
  "services": [
    {
      "id": 1,
      "title": "полірування",
      "img": "plies_ceramic.jpg",
      "icon": "poliruvanna.png",
      "prices": [
        { "type": "Полірування авто", "price": 3000 },
        { "type": "Полірування фар", "price": 500 },
        { "type": "Полірування одного елементу", "price": 300 }
      ]
    },
    {
      "id": 2,
      "title": "плівка",
      "img": "polishing_car.jpg",
      "icon": "plivka.png",
      "prices": [{ "type": "Поклейка фар", "price": 1500 }]
    },
    {
      "id": 3,
      "title": "хімчистка",
      "img": "spraying_car.jpg",
      "icon": "optika.png",
      "prices": [{ "type": "Хімчистка авто", "price": 1000 }]
    }
  ]
}
